README.md
setup.py
src/bitcoin.py
src/bitcoinUsingIFTTT.egg-info/PKG-INFO
src/bitcoinUsingIFTTT.egg-info/SOURCES.txt
src/bitcoinUsingIFTTT.egg-info/dependency_links.txt
src/bitcoinUsingIFTTT.egg-info/requires.txt
src/bitcoinUsingIFTTT.egg-info/top_level.txt