Metadata-Version: 2.1
Name: bitcoinUsingIFTTT
Version: 1.3
Summary: A package that allows to sent bitcoin alerts throgh IFTTT
Home-page: https://github.com/praveenNagaraj97-au7/bitcoinAlertWithTelegram
Author: Praveen
Author-email: praveenacchusn123@gmail.com
License: UNKNOWN
Platform: UNKNOWN
Classifier: Programming Language :: Python :: 3
Classifier: License :: OSI Approved :: MIT License
Classifier: Operating System :: OS Independent
